cm_tpm/__init__.py
cm_tpm/_cm.py
cm_tpm/_helpers.py
cm_tpm/_model.py
cm_tpm/cpp/_add.cp310-win_amd64.pyd
cm_tpm/cpp/add.cpp
cm_tpm-1.0.2.dist-info/licenses/LICENSE
cm_tpm-1.0.2.dist-info/METADATA
cm_tpm-1.0.2.dist-info/WHEEL
cm_tpm-1.0.2.dist-info/top_level.txt
cm_tpm-1.0.2.dist-info/RECORD
