Metadata-Version: 2.4
Name: cm-tpm
Version: 1.0.2
Summary: A Python package for data imputation using Continuous Mixtures of Tractable Probabilistic Models
Author-email: Hakim Agni <h.agni2001@gmail.com>
License: MIT License
Requires-Python: >=3.10
License-File: LICENSE
Requires-Dist: numpy>=1.22.4
Requires-Dist: pandas>=2.2.2
Requires-Dist: scipy>=1.13.0
Requires-Dist: torch>=2.6.0
Provides-Extra: excel
Requires-Dist: openpyxl>=3.1.2; extra == "excel"
Provides-Extra: parquet
Requires-Dist: pyarrow>=15.0.0; extra == "parquet"
Provides-Extra: feather
Requires-Dist: pyarrow>=15.0.0; extra == "feather"
Provides-Extra: tqdm
Requires-Dist: tqdm>=4.1.0; extra == "tqdm"
Provides-Extra: all
Requires-Dist: openpyxl>=3.1.2; extra == "all"
Requires-Dist: pyarrow>=15.0.0; extra == "all"
Requires-Dist: tqdm>=4.1.0; extra == "all"
Dynamic: license-file
